linder/__init__.py
linder/_env.py
linder/_linder_module.py
linder/_version.py
linder/clip_util.py
linder/fraction_util.py
linder/get_land_cover.py
linder/grass_util.py
linder/linder_version.json
linder/model.pkl
linder/other_util.py
linder/predict_util.py
linder/road_width.json
linder/sent_util.py
linder/setting.json
linder/task_util.py
linder-2020.6.3.2.dist-info/METADATA
linder-2020.6.3.2.dist-info/WHEEL
linder-2020.6.3.2.dist-info/top_level.txt
linder-2020.6.3.2.dist-info/RECORD
