Metadata-Version: 2.1
Name: linder
Version: 2020.6.3.2
Summary: linder is a machine-learning based land use/land cover (LULC) classifier using Sentinel imagery.
Home-page: UNKNOWN
Author: Dr Hamidreza Omidvar, Dr Ting Sun
Author-email: h.omidvar@reading.ac.uk, ting.sun@reading.ac.uk
License: GPL-V3.0
Platform: UNKNOWN
Classifier: Programming Language :: Python :: 3 :: Only
Classifier: Programming Language :: Python :: 3.6
Classifier: Programming Language :: Python :: 3.7
Classifier: Intended Audience :: Education
Classifier: Intended Audience :: Science/Research
Classifier: Operating System :: MacOS :: MacOS X
Classifier: Operating System :: Microsoft :: Windows
Classifier: Operating System :: POSIX :: Linux
Requires-Python: ~=3.6
Requires-Dist: numpy
Requires-Dist: pandas
Requires-Dist: scipy
Requires-Dist: scikit-learn
Requires-Dist: matplotlib
Requires-Dist: eo-learn
Requires-Dist: xarray
Requires-Dist: click
